ptrnets/__init__.py
ptrnets/cores/__init__.py
ptrnets/cores/cores.py
ptrnets/utils/__init__.py
ptrnets/utils/config.py
ptrnets/utils/gdrive.py
ptrnets/utils/mlayer.py
ptrnets/utils/modules.py
ptrnets/zoo/__init__.py
ptrnets/zoo/cifar10.py
ptrnets/zoo/config.toml
ptrnets/zoo/cornet.py
ptrnets/zoo/robust.py
ptrnets/zoo/shape_biased.py
ptrnets/zoo/simclr.py
ptrnets/zoo/taskonomy.py
ptrnets/zoo/third_party/README.md
ptrnets/zoo/third_party/__init__.py
ptrnets/zoo/third_party/cornet/__init__.py
ptrnets/zoo/third_party/cornet/cornet_r.py
ptrnets/zoo/third_party/cornet/cornet_rt.py
ptrnets/zoo/third_party/cornet/cornet_s.py
ptrnets/zoo/third_party/cornet/cornet_z.py
ptrnets/zoo/third_party/taskonomy/__init__.py
ptrnets/zoo/third_party/taskonomy/networks.py
ptrnets/zoo/vgg_original.py
ptrnets-0.1.1.dist-info/LICENSE
ptrnets-0.1.1.dist-info/METADATA
ptrnets-0.1.1.dist-info/WHEEL
ptrnets-0.1.1.dist-info/RECORD
