Metadata-Version: 2.1
Name: ptrnets
Version: 0.1.1
Summary: Easy access to pretrained models for system identification
Home-page: https://github.com/sacadena/ptrnets
Author: Santiago Cadena
Requires-Python: >=3.8,<3.11
Classifier: Programming Language :: Python :: 3
Classifier: Programming Language :: Python :: 3.8
Classifier: Programming Language :: Python :: 3.9
Classifier: Programming Language :: Python :: 3.10
Requires-Dist: gdown (>=4.5.1)
Requires-Dist: tomli (>=1.0.0)
Requires-Dist: torch (>=1.4.0,<2.0.0)
Requires-Dist: torchvision (>=0.5.0,<0.15.0)
Project-URL: Repository, https://github.com/sacadena/ptrnets
